{
    "categories": [
        "Austria",
        "Belgium",
        "Bulgaria",
        "Croatia",
        "Cyprus",
        "Czechia",
        "Denmark",
        "Estonia",
        "Finland",
        "France",
        "Germany",
        "Greece",
        "Hungary",
        "Ireland",
        "Italy",
        "Latvia",
        "Lithuania",
        "Luxembourg",
        "Malta",
        "Netherlands",
        "Poland",
        "Portugal",
        "Romania",
        "Slovakia",
        "Slovenia",
        "Spain",
        "Sweden",
        "United Kingdom"
    ],
    "data": [
        {
            "year": "2008",
            "series": [
                {
                    "name": "agriculture",
                    "data": [
                        6568.5,
                        8051.6,
                        4914.6,
                        3288.4,
                        733.4,
                        6174.7,
                        8200.0,
                        671.4,
                        4357.0,
                        72311.0,
                        45795.0,
                        11111.3,
                        8943.0,
                        6462.5,
                        51394.8,
                        1130.0,
                        2474.8,
                        363.7,
                        149.5,
                        27445.0,
                        24175.0,
                        6231.1,
                        19130.9,
                        2832.4,
                        1249.4,
                        42938.0,
                        7074.0,
                        27798.0
                    ]
                }
            ]
        },
        {
            "year": "2009",
            "series": [
                {
                    "name": "agriculture",
                    "data": [
                        5979.5,
                        7494.5,
                        4080.7,
                        3121.7,
                        712.2,
                        5032.4,
                        7851.9,
                        570.9,
                        4144.0,
                        67011.0,
                        39697.0,
                        10717.2,
                        7223.2,
                        5057.8,
                        47343.6,
                        962.0,
                        1864.8,
                        323.2,
                        147.8,
                        25846.0,
                        19312.1,
                        5880.9,
                        15198.9,
                        2322.6,
                        1138.4,
                        39466.0,
                        6037.0,
                        25101.6
                    ]
                }
            ]
        },
        {
            "year": "2010",
            "series": [
                {
                    "name": "agriculture",
                    "data": [
                        6400.2,
                        8444.4,
                        3967.5,
                        2972.0,
                        745.7,
                        5072.2,
                        8770.8,
                        671.2,
                        4383.0,
                        71895.0,
                        45568.0,
                        11002.8,
                        7241.7,
                        5481.5,
                        48052.7,
                        1043.6,
                        2106.3,
                        325.6,
                        146.4,
                        28053.0,
                        21902.0,
                        6037.6,
                        13815.5,
                        2218.1,
                        1184.5,
                        42452.0,
                        7999.9,
                        26212.3
                    ]
                }
            ]
        },
        {
            "year": "2011",
            "series": [
                {
                    "name": "agriculture",
                    "data": [
                        7225.1,
                        8736.4,
                        4559.3,
                        2947.0,
                        759.7,
                        6960.0,
                        9657.2,
                        814.2,
                        4740.0,
                        77350.0,
                        51147.0,
                        11062.2,
                        8960.2,
                        6998.5,
                        52296.7,
                        1145.2,
                        2662.7,
                        348.3,
                        149.0,
                        28604.0,
                        25610.6,
                        6079.8,
                        15688.7,
                        2709.9,
                        1312.9,
                        43340.0,
                        8839.3,
                        28399.1
                    ]
                }
            ]
        },
        {
            "year": "2012",
            "series": [
                {
                    "name": "agriculture",
                    "data": [
                        7305.1,
                        9683.3,
                        4484.6,
                        2806.5,
                        715.4,
                        7246.8,
                        10733.4,
                        902.1,
                        4995.0,
                        80858.0,
                        50826.0,
                        11097.1,
                        8805.3,
                        6999.4,
                        54226.3,
                        1393.2,
                        2982.8,
                        430.3,
                        148.8,
                        29575.0,
                        25939.0,
                        6211.3,
                        11953.1,
                        2957.3,
                        1227.9,
                        43537.0,
                        9133.9,
                        30853.3
                    ]
                }
            ]
        },
        {
            "year": "2013",
            "series": [
                {
                    "name": "agriculture",
                    "data": [
                        7080.9,
                        9569.6,
                        4372.4,
                        2659.1,
                        683.7,
                        7322.5,
                        10043.3,
                        928.2,
                        4994.0,
                        78643.0,
                        55304.0,
                        10930.1,
                        9111.6,
                        7863.4,
                        57020.3,
                        1392.6,
                        2872.9,
                        445.1,
                        152.5,
                        31091.0,
                        26762.8,
                        6323.0,
                        14893.7,
                        3106.4,
                        1232.9,
                        47613.0,
                        9143.5,
                        30592.5
                    ]
                }
            ]
        },
        {
            "year": "2014",
            "series": [
                {
                    "name": "agriculture",
                    "data": [
                        7032.7,
                        9142.1,
                        4311.2,
                        2261.3,
                        657.1,
                        7306.8,
                        10118.8,
                        905.7,
                        4770.0,
                        79523.0,
                        54330.0,
                        11084.0,
                        9123.3,
                        7681.8,
                        54319.0,
                        1345.7,
                        2832.6,
                        458.9,
                        143.3,
                        29950.0,
                        26555.7,
                        6417.3,
                        13994.3,
                        3446.8,
                        1296.4,
                        45622.0,
                        8864.3,
                        32730.9
                    ]
                }
            ]
        },
        {
            "year": "2015",
            "series": [
                {
                    "name": "agriculture",
                    "data": [
                        6808.5,
                        9297.4,
                        4041.8,
                        2281.6,
                        686.4,
                        7382.1,
                        9218.6,
                        941.2,
                        4486.0,
                        79579.0,
                        48306.0,
                        11572.3,
                        9189.9,
                        7613.4,
                        55460.6,
                        1494.8,
                        2972.4,
                        404.5,
                        144.9,
                        29594.0,
                        24491.0,
                        6631.7,
                        12766.7,
                        3293.7,
                        1340.1,
                        50116.0,
                        8653.7,
                        36794.6
                    ]
                }
            ]
        },
        {
            "year": "2016",
            "series": [
                {
                    "name": "agriculture",
                    "data": [
                        6874.9,
                        9164.1,
                        3988.4,
                        2409.5,
                        701.6,
                        7234.0,
                        9113.5,
                        752.7,
                        4494.0,
                        75073.0,
                        48121.0,
                        11204.6,
                        9485.8,
                        7826.5,
                        53466.8,
                        1408.0,
                        2852.2,
                        406.5,
                        151.5,
                        29972.0,
                        24513.2,
                        6634.7,
                        12891.8,
                        3328.4,
                        1289.3,
                        51439.0,
                        8713.4,
                        32454.7
                    ]
                }
            ]
        },
        {
            "year": "2017",
            "series": [
                {
                    "name": "agriculture",
                    "data": [
                        7346.6,
                        9544.0,
                        4320.0,
                        2398.2,
                        735.8,
                        7768.1,
                        10320.1,
                        890.1,
                        4493.0,
                        77731.0,
                        53301.0,
                        11802.3,
                        9746.1,
                        8994.9,
                        53466.8,
                        1505.2,
                        3156.1,
                        429.2,
                        144.0,
                        31957.0,
                        28264.7,
                        7074.2,
                        14685.3,
                        3258.6,
                        1213.5,
                        53322.0,
                        9256.8,
                        32454.7
                    ]
                }
            ]
        }
    ]
}